README.md
setup.py
functionsproject.egg-info/PKG-INFO
functionsproject.egg-info/SOURCES.txt
functionsproject.egg-info/dependency_links.txt
functionsproject.egg-info/not-zip-safe
functionsproject.egg-info/top_level.txt
src/__init__.py
src/functions.py
src/greet.py
src/test.py