Metadata-Version: 2.1
Name: functionsproject
Version: 0.1
Summary: Testing installation of Package
Home-page: 
Author: Vismaya
Author-email: muruganvichunni@gmail.com
License: MIT
